<DOMSymbolItem xmlns:xsi="http://www.w3.org/2001/XMLSchema-instance" xmlns="http://ns.adobe.com/xfl/2008/" name="coin_icon_mc" itemID="60f7b569-000001cf" linkageExportForAS="true" linkageClassName="coin_icon_mc" lastModified="1626869456">
  <timeline>
    <DOMTimeline name="coin_icon_mc">
      <layers>
        <DOMLayer name="图层 1" color="#4F80FF" current="true" isSelected="true">
          <frames>
            <DOMFrame index="0" keyMode="9728">
              <elements>
                <DOMBitmapInstance libraryItemName="coin_ico.png"/>
              </elements>
            </DOMFrame>
          </frames>
        </DOMLayer>
      </layers>
    </DOMTimeline>
  </timeline>
</DOMSymbolItem>