<DOMSymbolItem xmlns:xsi="http://www.w3.org/2001/XMLSchema-instance" xmlns="http://ns.adobe.com/xfl/2008/" name="元件 49" itemID="5227f302-0000099e" symbolType="graphic" lastModified="1378349849">
  <timeline>
    <DOMTimeline name="元件 49">
      <layers>
        <DOMLayer name="图层 1" color="#4FFF4F" current="true" isSelected="true">
          <frames>
            <DOMFrame index="0" duration="2" keyMode="9728">
              <elements>
                <DOMBitmapInstance libraryItemName="Fireworks 对象/复制/复制 13/位图 1656">
                  <matrix>
                    <Matrix tx="107.5" ty="7"/>
                  </matrix>
                </DOMBitmapInstance>
              </elements>
            </DOMFrame>
            <DOMFrame index="2" duration="2" keyMode="9728">
              <elements>
                <DOMBitmapInstance libraryItemName="Fireworks 对象/复制/复制 13/位图 1655">
                  <matrix>
                    <Matrix tx="116" ty="5"/>
                  </matrix>
                </DOMBitmapInstance>
              </elements>
            </DOMFrame>
            <DOMFrame index="4" duration="2" keyMode="9728">
              <elements>
                <DOMBitmapInstance selected="true" libraryItemName="Fireworks 对象/复制/复制 13/位图 1654">
                  <matrix>
                    <Matrix tx="123.5"/>
                  </matrix>
                </DOMBitmapInstance>
              </elements>
            </DOMFrame>
            <DOMFrame index="6" duration="2" keyMode="9728">
              <elements>
                <DOMBitmapInstance libraryItemName="Fireworks 对象/复制/复制 13/位图 1653">
                  <matrix>
                    <Matrix tx="127.5" ty="16"/>
                  </matrix>
                </DOMBitmapInstance>
              </elements>
            </DOMFrame>
            <DOMFrame index="8" keyMode="9728">
              <elements/>
            </DOMFrame>
          </frames>
        </DOMLayer>
      </layers>
    </DOMTimeline>
  </timeline>
</DOMSymbolItem>